{
   "ExcludeInterfaces" : [ "lo", "eth0", "lxcbr0", "eth1" ],
   "InterfaceModes" : { "wlan0":"Multicast", "emane1":"Multicast", "emane2":"Multicast", "emane3":"Multicast", "emane4":"Multicast", "emane5":"Multicast" },
   "FragmentSize" : 50000,
   "TargetTxRateBps" : 50000,
   "PrintLogs" : "yes",
   "LogEvents" : "no",
   "EmulatePacketDrops" : "no",
   "SignalingMode" : "proactive",
   "DestFileFolder" : "./data/",
   "ServerCloudMode" : "no",
   "BabelRouting" : "yes",
   "BabelPeriod" : 30000,
   "BabelDeleteRoutes" : "no",
   "BabelInvalidatePeriod" : 12,
   "BabelDeletePeriod" : 24,
   "HandshakeReactivePeriod" : 10000,
   "HandshakePeriod" : 5000,
   "BeaconPeriod" : 5000,
   "DataPerishable" : "no",
   "DataPerishableTime" : 1,
   "OverhearingData" : "yes",
   "GvineChecksums" : "yes",
   "GvineEncryption" : "no",
   "GvineRoutingPubKey" : "no",
   "GvineAcknowledgments" : "no",
   "GvineUnicastGW" : "no",
   "GvineUnicastIP" : "10.0.1.2",
   "GvineDataBroadcasts" : "no",
   "GvineDataMulticasts" : "yes",
   "GvineMulticastGw" : "no",
   "GvineMulticastGwIp" : "224.1.0.1",
   "GvineMulticastGwIpListen" : [ "224.1.0.2" ]
}
